setup.py
erucli/__init__.py
erucli.egg-info/PKG-INFO
erucli.egg-info/SOURCES.txt
erucli.egg-info/dependency_links.txt
erucli.egg-info/entry_points.txt
erucli.egg-info/not-zip-safe
erucli.egg-info/requires.txt
erucli.egg-info/top_level.txt
erucli/console/__init__.py
erucli/console/app.py
erucli/console/cmdline.py
erucli/console/commands.py
erucli/console/entity.py
erucli/console/output.py
erucli/console/style.py