Metadata-Version: 1.0
Name: erucli
Version: 0.1.24
Summary: ERU command line tool
Home-page: UNKNOWN
Author: tonic
Author-email: tonic@wolege.ca
License: UNKNOWN
Platform: UNKNOWN
